pandas_tfrecords/__init__.py
pandas_tfrecords/from_tfrecords.py
pandas_tfrecords/to_tfrecords.py
pandas_tfrecords-0.1.6.dist-info/LICENSE
pandas_tfrecords-0.1.6.dist-info/METADATA
pandas_tfrecords-0.1.6.dist-info/WHEEL
pandas_tfrecords-0.1.6.dist-info/top_level.txt
pandas_tfrecords-0.1.6.dist-info/RECORD
