Metadata-Version: 2.1
Name: pandas-tfrecords
Version: 0.1.6
Summary: Converter pandas to tfrecords & tfrecords to pandas
Home-page: https://github.com/schipiga/pandas-tfrecords/
Author: Sergei Chipiga
Author-email: chipiga86@gmail.com
License: MIT
Platform: UNKNOWN
Classifier: License :: OSI Approved :: MIT License
Classifier: Programming Language :: Python :: 3
Classifier: Programming Language :: Python :: 3.6
Classifier: Programming Language :: Python :: 3.7
License-File: LICENSE
Requires-Dist: s3fs
Requires-Dist: tensorflow
Requires-Dist: pandas
Requires-Dist: numpy
